pico8/__init__.py
pico8/pico8.py
pico8_mkdocs_plugin-1.0.0.dist-info/LICENSE
pico8_mkdocs_plugin-1.0.0.dist-info/METADATA
pico8_mkdocs_plugin-1.0.0.dist-info/WHEEL
pico8_mkdocs_plugin-1.0.0.dist-info/entry_points.txt
pico8_mkdocs_plugin-1.0.0.dist-info/top_level.txt
pico8_mkdocs_plugin-1.0.0.dist-info/RECORD
