Metadata-Version: 2.1
Name: pico8-mkdocs-plugin
Version: 1.0.0
Summary: This plugin allows to embed a Pico-8 web player in a mkdocs generated page.
Home-page: https://github.com/fmaida/pico8-mkdocs-plugin
Author: Francesco Maida
Author-email: francesco.maida@gmail.com
License: MIT
Platform: UNKNOWN
Requires-Dist: mkdocs
